algebraixlib/__init__.py
algebraixlib/cache_status.py
algebraixlib/extension.py
algebraixlib/partition.py
algebraixlib/structure.py
algebraixlib/tmp_sqlda_op.py
algebraixlib/undef.py
algebraixlib/algebras/__init__.py
algebraixlib/algebras/clans.py
algebraixlib/algebras/couplets.py
algebraixlib/algebras/multiclans.py
algebraixlib/algebras/multisets.py
algebraixlib/algebras/properties.py
algebraixlib/algebras/relations.py
algebraixlib/algebras/sets.py
algebraixlib/import_export/__init__.py
algebraixlib/import_export/_util.py
algebraixlib/import_export/csv.py
algebraixlib/import_export/json.py
algebraixlib/import_export/mojson.py
algebraixlib/import_export/rdf.py
algebraixlib/import_export/xml.py
algebraixlib/mathobjects/__init__.py
algebraixlib/mathobjects/_flags.py
algebraixlib/mathobjects/atom.py
algebraixlib/mathobjects/couplet.py
algebraixlib/mathobjects/mathobject.py
algebraixlib/mathobjects/multiset.py
algebraixlib/mathobjects/set.py
algebraixlib/util/__init__.py
algebraixlib/util/html.py
algebraixlib/util/latexprinter.py
algebraixlib/util/mathobjectprinter.py
algebraixlib/util/miscellaneous.py
algebraixlib/util/rdf.py
algebraixlib/util/test.py
algebraixlib-1.4.dist-info/DESCRIPTION.rst
algebraixlib-1.4.dist-info/METADATA
algebraixlib-1.4.dist-info/RECORD
algebraixlib-1.4.dist-info/WHEEL
algebraixlib-1.4.dist-info/metadata.json
algebraixlib-1.4.dist-info/top_level.txt
